Metadata-Version: 2.4
Name: bitbytelab
Version: 0.1.0
Summary: A collection of reusable utility functions and modules.
Project-URL: Homepage, https://github.com/bitbytelab/bblab
Project-URL: Issues, https://github.com/bitbytelab/bblab/issues
Author-email: Hasan Rasel <rrss.mahmud@gmail.com>
License-Expression: MIT
License-File: LICENSE
License-File: LICENSE.txt
Keywords: bblab,bitbytelab,python,utility,utils
Classifier: Operating System :: OS Independent
Classifier: Programming Language :: Python :: 3.10
Classifier: Programming Language :: Python :: 3.11
Classifier: Programming Language :: Python :: 3.12
Classifier: Programming Language :: Python :: 3.13
Classifier: Topic :: Software Development :: Libraries :: Python Modules
Requires-Python: >=3.10
Requires-Dist: colorlog
Requires-Dist: joblib
Requires-Dist: pandas
Requires-Dist: pyjwt
Requires-Dist: python-dotenv
Requires-Dist: requests
Provides-Extra: dev
Requires-Dist: hatchling; extra == 'dev'
Requires-Dist: uv-dynamic-versioning; extra == 'dev'
